odoo/addons/sign_oca/README.rst
odoo/addons/sign_oca/__init__.py
odoo/addons/sign_oca/__manifest__.py
odoo/addons/sign_oca/controllers/__init__.py
odoo/addons/sign_oca/controllers/main.py
odoo/addons/sign_oca/data/data.xml
odoo/addons/sign_oca/demo/sign_oca_template.xml
odoo/addons/sign_oca/i18n/ca.po
odoo/addons/sign_oca/i18n/es.po
odoo/addons/sign_oca/i18n/it.po
odoo/addons/sign_oca/i18n/pt_BR.po
odoo/addons/sign_oca/i18n/sign_oca.pot
odoo/addons/sign_oca/models/__init__.py
odoo/addons/sign_oca/models/res_partner.py
odoo/addons/sign_oca/models/res_users.py
odoo/addons/sign_oca/models/sign_oca_field.py
odoo/addons/sign_oca/models/sign_oca_request.py
odoo/addons/sign_oca/models/sign_oca_role.py
odoo/addons/sign_oca/models/sign_oca_template.py
odoo/addons/sign_oca/readme/CONFIGURE.rst
odoo/addons/sign_oca/readme/CONTRIBUTORS.rst
odoo/addons/sign_oca/readme/DESCRIPTION.rst
odoo/addons/sign_oca/readme/ROADMAP.rst
odoo/addons/sign_oca/readme/USAGE.rst
odoo/addons/sign_oca/security/ir.model.access.csv
odoo/addons/sign_oca/security/security.xml
odoo/addons/sign_oca/static/description.svg
odoo/addons/sign_oca/static/description/icon.png
odoo/addons/sign_oca/static/description/icon.svg
odoo/addons/sign_oca/static/description/index.html
odoo/addons/sign_oca/static/src/components/sign_oca_configure/sign_oca_configure.js
odoo/addons/sign_oca/static/src/components/sign_oca_configure/sign_oca_configure.xml
odoo/addons/sign_oca/static/src/components/sign_oca_pdf/sign_oca_pdf.js
odoo/addons/sign_oca/static/src/components/sign_oca_pdf/sign_oca_pdf.xml
odoo/addons/sign_oca/static/src/components/sign_oca_pdf/sign_oca_pdf_action.js
odoo/addons/sign_oca/static/src/components/sign_oca_pdf_common/sign_oca_pdf_common.js
odoo/addons/sign_oca/static/src/components/sign_oca_pdf_common/sign_oca_pdf_common.xml
odoo/addons/sign_oca/static/src/components/sign_oca_pdf_common/sign_oca_pdf_common_action.js
odoo/addons/sign_oca/static/src/components/sign_oca_pdf_portal/sign_oca_pdf_portal.js
odoo14_addon_sign_oca-14.0.2.4.7.dist-info/METADATA
odoo14_addon_sign_oca-14.0.2.4.7.dist-info/WHEEL
odoo14_addon_sign_oca-14.0.2.4.7.dist-info/top_level.txt
odoo14_addon_sign_oca-14.0.2.4.7.dist-info/RECORD
