Metadata-Version: 2.1
Name: odoo14-addon-sign_oca
Version: 14.0.2.4.7
Summary: Allow to sign documents inside Odoo CE
Home-page: https://github.com/OCA/sign
Author: Dixmit,Odoo Community Association (OCA)
Author-email: support@odoo-community.org
License: AGPL-3
Classifier: Programming Language :: Python
Classifier: Framework :: Odoo
Classifier: Framework :: Odoo :: 14.0
Classifier: License :: OSI Approved :: GNU Affero General Public License v3
Requires-Python: >=3.6
Requires-Dist: odoo <14.1dev,>=14.0a
